{
	"info": {
		"_postman_id": "12345678-1234-1234-1234-123456789abc",
		"name": "Yatube API",
		"description": "Коллекция запросов для тестирования API проекта Yatube",
		"schema": "https://schema.getpostman.com/json/collection/v2.1.0/collection.json"
	},
	"item": [
		{
			"name": "Auth",
			"item": [
				{
					"name": "Get Token",
					"event": [
						{
							"listen": "test",
							"script": {
								"exec": [
									"pm.test(\"Status code is 200\", function () {",
									"    pm.response.to.have.status(200);",
									"});",
									"",
									"pm.test(\"Token is present\", function () {",
									"    var jsonData = pm.response.json();",
									"    pm.expect(jsonData).to.have.property('token');",
									"    pm.environment.set(\"auth_token\", jsonData.token);",
									"});"
								],
								"type": "text/javascript"
							}
						}
					],
					"request": {
						"method": "POST",
						"header": [
							{
								"key": "Content-Type",
								"value": "application/json"
							}
						],
						"body": {
							"mode": "raw",
							"raw": "{\n    \"username\": \"testuser\",\n    \"password\": \"testpass123\"\n}"
						},
						"url": {
							"raw": "http://localhost:8000/api/v1/api-token-auth/",
							"protocol": "http",
							"host": [
								"localhost"
							],
							"port": "8000",
							"path": [
								"api",
								"v1",
								"api-token-auth",
								""
							]
						}
					},
					"response": []
				}
			]
		},
		{
			"name": "Groups",
			"item": [
				{
					"name": "Get All Groups",
					"event": [
						{
							"listen": "test",
							"script": {
								"exec": [
									"pm.test(\"Status code is 200\", function () {",
									"    pm.response.to.have.status(200);",
									"});",
									"",
									"pm.test(\"Groups array is not empty\", function () {",
									"    var jsonData = pm.response.json();",
									"    pm.expect(jsonData.results).to.be.an('array');",
									"    pm.expect(jsonData.results.length).to.be.above(0);",
									"    if (jsonData.results.length > 0) {",
									"        pm.environment.set(\"group_id\", jsonData.results[0].id);",
									"    }",
									"});"
								],
								"type": "text/javascript"
							}
						}
					],
					"request": {
						"method": "GET",
						"header": [],
						"url": {
							"raw": "http://localhost:8000/api/v1/groups/",
							"protocol": "http",
							"host": [
								"localhost"
							],
							"port": "8000",
							"path": [
								"api",
								"v1",
								"groups",
								""
							]
						}
					},
					"response": []
				},
				{
					"name": "Get Group by ID",
					"event": [
						{
							"listen": "test",
							"script": {
								"exec": [
									"pm.test(\"Status code is 200\", function () {",
									"    pm.response.to.have.status(200);",
									"});",
									"",
									"pm.test(\"Group has required fields\", function () {",
									"    var jsonData = pm.response.json();",
									"    pm.expect(jsonData).to.have.property('id');",
									"    pm.expect(jsonData).to.have.property('title');",
									"    pm.expect(jsonData).to.have.property('slug');",
									"    pm.expect(jsonData).to.have.property('description');",
									"});"
								],
								"type": "text/javascript"
							}
						}
					],
					"request": {
						"method": "GET",
						"header": [],
						"url": {
							"raw": "http://localhost:8000/api/v1/groups/2/",
							"protocol": "http",
							"host": [
								"localhost"
							],
							"port": "8000",
							"path": [
								"api",
								"v1",
								"groups",
								"2",
								""
							]
						}
					},
					"response": []
				}
			]
		},
		{
			"name": "Posts",
			"item": [
				{
					"name": "Get All Posts",
					"event": [
						{
							"listen": "test",
							"script": {
								"exec": [
									"pm.test(\"Status code is 200\", function () {",
									"    pm.response.to.have.status(200);",
									"});",
									"",
									"pm.test(\"Posts array is not empty\", function () {",
									"    var jsonData = pm.response.json();",
									"    pm.expect(jsonData.results).to.be.an('array');",
									"    pm.expect(jsonData.results.length).to.be.above(0);",
									"    if (jsonData.results.length > 0) {",
									"        pm.environment.set(\"post_id\", jsonData.results[0].id);",
									"    }",
									"});"
								],
								"type": "text/javascript"
							}
						}
					],
					"request": {
						"method": "GET",
						"header": [],
						"url": {
							"raw": "http://localhost:8000/api/v1/posts/",
							"protocol": "http",
							"host": [
								"localhost"
							],
							"port": "8000",
							"path": [
								"api",
								"v1",
								"posts",
								""
							]
						}
					},
					"response": []
				},
				{
					"name": "Create Post",
					"event": [
						{
							"listen": "test",
							"script": {
								"exec": [
									"pm.test(\"Status code is 201\", function () {",
									"    pm.response.to.have.status(201);",
									"});",
									"",
									"pm.test(\"Post created successfully\", function () {",
									"    var jsonData = pm.response.json();",
									"    pm.expect(jsonData).to.have.property('id');",
									"    pm.expect(jsonData).to.have.property('text');",
									"    pm.expect(jsonData.author).to.eql('testuser');",
									"    pm.environment.set(\"created_post_id\", jsonData.id);",
									"});"
								],
								"type": "text/javascript"
							}
						}
					],
					"request": {
						"method": "POST",
						"header": [
							{
								"key": "Content-Type",
								"value": "application/json"
							},
							{
								"key": "Authorization",
								"value": "Token {{auth_token}}"
							}
						],
						"body": {
							"mode": "raw",
							"raw": "{\n    \"text\": \"Новый пост через API\",\n    \"group\": 1\n}"
						},
						"url": {
							"raw": "http://localhost:8000/api/v1/posts/",
							"protocol": "http",
							"host": [
								"localhost"
							],
							"port": "8000",
							"path": [
								"api",
								"v1",
								"posts",
								""
							]
						}
					},
					"response": []
				},
				{
					"name": "Get Post by ID",
					"event": [
						{
							"listen": "test",
							"script": {
								"exec": [
									"pm.test(\"Status code is 200\", function () {",
									"    pm.response.to.have.status(200);",
									"});",
									"",
									"pm.test(\"Post has required fields\", function () {",
									"    var jsonData = pm.response.json();",
									"    pm.expect(jsonData).to.have.property('id');",
									"    pm.expect(jsonData).to.have.property('text');",
									"    pm.expect(jsonData).to.have.property('author');",
									"});"
								],
								"type": "text/javascript"
							}
						}
					],
					"request": {
						"method": "GET",
						"header": [
							{
								"key": "Authorization",
								"value": "Token {{auth_token}}"
							}
						],
						"url": {
							"raw": "http://localhost:8000/api/v1/posts/{{post_id}}/",
							"protocol": "http",
							"host": [
								"localhost"
							],
							"port": "8000",
							"path": [
								"api",
								"v1",
								"posts",
								"{{post_id}}",
								""
							]
						}
					},
					"response": []
				},
				{
					"name": "Update Post",
					"event": [
						{
							"listen": "test",
							"script": {
								"exec": [
									"pm.test(\"Status code is 200\", function () {",
									"    pm.response.to.have.status(200);",
									"});",
									"",
									"pm.test(\"Post updated successfully\", function () {",
									"    var jsonData = pm.response.json();",
									"    pm.expect(jsonData.text).to.include('Обновленный');",
									"});"
								],
								"type": "text/javascript"
							}
						}
					],
					"request": {
						"method": "PUT",
						"header": [
							{
								"key": "Content-Type",
								"value": "application/json"
							},
							{
								"key": "Authorization",
								"value": "Token {{auth_token}}"
							}
						],
						"body": {
							"mode": "raw",
							"raw": "{\n    \"text\": \"Обновленный текст поста\"\n}"
						},
						"url": {
							"raw": "http://localhost:8000/api/v1/posts/{{created_post_id}}/",
							"protocol": "http",
							"host": [
								"localhost"
							],
							"port": "8000",
							"path": [
								"api",
								"v1",
								"posts",
								"{{created_post_id}}",
								""
							]
						}
					},
					"response": []
				},
				{
					"name": "Partial Update Post",
					"event": [
						{
							"listen": "test",
							"script": {
								"exec": [
									"pm.test(\"Status code is 200\", function () {",
									"    pm.response.to.have.status(200);",
									"});"
								],
								"type": "text/javascript"
							}
						}
					],
					"request": {
						"method": "PATCH",
						"header": [
							{
								"key": "Content-Type",
								"value": "application/json"
							},
							{
								"key": "Authorization",
								"value": "Token {{auth_token}}"
							}
						],
						"body": {
							"mode": "raw",
							"raw": "{\n    \"text\": \"Частично обновленный текст\"\n}"
						},
						"url": {
							"raw": "http://localhost:8000/api/v1/posts/{{created_post_id}}/",
							"protocol": "http",
							"host": [
								"localhost"
							],
							"port": "8000",
							"path": [
								"api",
								"v1",
								"posts",
								"{{created_post_id}}",
								""
							]
						}
					},
					"response": []
				},
				{
					"name": "Delete Post",
					"event": [
						{
							"listen": "test",
							"script": {
								"exec": [
									"pm.test(\"Status code is 204\", function () {",
									"    pm.response.to.have.status(204);",
									"});"
								],
								"type": "text/javascript"
							}
						}
					],
					"request": {
						"method": "DELETE",
						"header": [
							{
								"key": "Authorization",
								"value": "Token {{auth_token}}"
							}
						],
						"url": {
							"raw": "http://localhost:8000/api/v1/posts/{{created_post_id}}/",
							"protocol": "http",
							"host": [
								"localhost"
							],
							"port": "8000",
							"path": [
								"api",
								"v1",
								"posts",
								"{{created_post_id}}",
								""
							]
						}
					},
					"response": []
				}
			]
		},
		{
			"name": "Comments",
			"item": [
				{
					"name": "Get Comments for Post",
					"event": [
						{
							"listen": "test",
							"script": {
								"exec": [
									"pm.test(\"Status code is 200\", function () {",
									"    pm.response.to.have.status(200);",
									"});",
									"",
									"pm.test(\"Comments is array\", function () {",
									"    var jsonData = pm.response.json();",
									"    pm.expect(jsonData.results).to.be.an('array');",
									"});"
								],
								"type": "text/javascript"
							}
						}
					],
					"request": {
						"method": "GET",
						"header": [],
						"url": {
							"raw": "http://localhost:8000/api/v1/posts/{{post_id}}/comments/",
							"protocol": "http",
							"host": [
								"localhost"
							],
							"port": "8000",
							"path": [
								"api",
								"v1",
								"posts",
								"{{post_id}}",
								"comments",
								""
							]
						}
					},
					"response": []
				},
				{
					"name": "Create Comment",
					"event": [
						{
							"listen": "test",
							"script": {
								"exec": [
									"pm.test(\"Status code is 201\", function () {",
									"    pm.response.to.have.status(201);",
									"});",
									"",
									"pm.test(\"Comment created successfully\", function () {",
									"    var jsonData = pm.response.json();",
									"    pm.expect(jsonData).to.have.property('id');",
									"    pm.expect(jsonData).to.have.property('text');",
									"    pm.expect(jsonData.author).to.eql('testuser');",
									"    pm.environment.set(\"comment_id\", jsonData.id);",
									"});"
								],
								"type": "text/javascript"
							}
						}
					],
					"request": {
						"method": "POST",
						"header": [
							{
								"key": "Content-Type",
								"value": "application/json"
							},
							{
								"key": "Authorization",
								"value": "Token {{auth_token}}"
							}
						],
						"body": {
							"mode": "raw",
							"raw": "{\n    \"text\": \"Новый комментарий через API\"\n}"
						},
						"url": {
							"raw": "http://localhost:8000/api/v1/posts/{{post_id}}/comments/",
							"protocol": "http",
							"host": [
								"localhost"
							],
							"port": "8000",
							"path": [
								"api",
								"v1",
								"posts",
								"{{post_id}}",
								"comments",
								""
							]
						}
					},
					"response": []
				},
				{
					"name": "Update Comment",
					"event": [
						{
							"listen": "test",
							"script": {
								"exec": [
									"pm.test(\"Status code is 200\", function () {",
									"    pm.response.to.have.status(200);",
									"});",
									"",
									"pm.test(\"Comment updated successfully\", function () {",
									"    var jsonData = pm.response.json();",
									"    pm.expect(jsonData.text).to.include('Обновленный');",
									"});"
								],
								"type": "text/javascript"
							}
						}
					],
					"request": {
						"method": "PUT",
						"header": [
							{
								"key": "Content-Type",
								"value": "application/json"
							},
							{
								"key": "Authorization",
								"value": "Token {{auth_token}}"
							}
						],
						"body": {
							"mode": "raw",
							"raw": "{\n    \"text\": \"Обновленный комментарий\"\n}"
						},
						"url": {
							"raw": "http://localhost:8000/api/v1/posts/{{post_id}}/comments/{{comment_id}}/",
							"protocol": "http",
							"host": [
								"localhost"
							],
							"port": "8000",
							"path": [
								"api",
								"v1",
								"posts",
								"{{post_id}}",
								"comments",
								"{{comment_id}}",
								""
							]
						}
					},
					"response": []
				},
				{
					"name": "Delete Comment",
					"event": [
						{
							"listen": "test",
							"script": {
								"exec": [
									"pm.test(\"Status code is 204\", function () {",
									"    pm.response.to.have.status(204);",
									"});"
								],
								"type": "text/javascript"
							}
						}
					],
					"request": {
						"method": "DELETE",
						"header": [
							{
								"key": "Authorization",
								"value": "Token {{auth_token}}"
							}
						],
						"url": {
							"raw": "http://localhost:8000/api/v1/posts/{{post_id}}/comments/{{comment_id}}/",
							"protocol": "http",
							"host": [
								"localhost"
							],
							"port": "8000",
							"path": [
								"api",
								"v1",
								"posts",
								"{{post_id}}",
								"comments",
								"{{comment_id}}",
								""
							]
						}
					},
					"response": []
				}
			]
		}
	]
}
